filmweb/__init__.py
filmweb/getter.py
filmweb/main.py
filmweb/parser.py
filmweb-0.10.dist-info/licenses/LICENSE
filmweb-0.10.dist-info/METADATA
filmweb-0.10.dist-info/WHEEL
filmweb-0.10.dist-info/entry_points.txt
filmweb-0.10.dist-info/top_level.txt
filmweb-0.10.dist-info/RECORD
