Metadata-Version: 2.4
Name: filmweb
Version: 0.10
Summary: Export movie ratings from filmweb.pl
Author: Piotr Patrzyk
License: MIT
Project-URL: Source, https://github.com/ppatrzyk/filmweb-export
Keywords: filmweb,movie,crawler,data
Classifier: Development Status :: 4 - Beta
Classifier: License :: OSI Approved :: MIT License
Classifier: Operating System :: OS Independent
Classifier: Programming Language :: Python :: 3
Classifier: Topic :: Internet
Requires-Python: >=3.10
License-File: LICENSE
Requires-Dist: certifi==2025.10.5
Requires-Dist: charset-normalizer==3.4.4
Requires-Dist: docopt==0.6.2
Requires-Dist: idna==3.11
Requires-Dist: requests==2.32.5
Requires-Dist: tqdm==4.67.1
Requires-Dist: urllib3==2.5.0
Dynamic: license-file
